pyloudness/__init__.py
pyloudness-1.1.0.dist-info/RECORD
pyloudness-1.1.0.dist-info/top_level.txt
pyloudness-1.1.0.dist-info/metadata.json
pyloudness-1.1.0.dist-info/WHEEL
pyloudness-1.1.0.dist-info/DESCRIPTION.rst
pyloudness-1.1.0.dist-info/METADATA
