Metadata-Version: 2.0
Name: pyloudness
Version: 1.1.0
Summary: Find out how loud that file is
Home-page: https://github.com/jrigden/pyloudness
Author: Jason Rigden
Author-email: jasonrigden@gmail.com
License: MIT
Keywords: loudness audio ebu r128
Platform: UNKNOWN
Classifier: Development Status :: 5 - Production/Stable
Classifier: Intended Audience :: Developers
Classifier: Topic :: Multimedia :: Sound/Audio :: Analysis
Classifier: License :: OSI Approved :: MIT License
